{
  "mongo_db": "legal_rag_runtime",
  "run_id": "467ac9956f7b465288d4f0426ad23405",
  "run_started_at": "2026-03-02 06:32:41.583000",
  "run_finished_at": "2026-03-02 06:34:54.277000",
  "run_stats": {
    "sources_total": 14,
    "docs_ok": 9,
    "docs_restricted": 3,
    "docs_error": 2,
    "pages_written": 309,
    "nodes_written": 1337,
    "citations_written": 0
  },
  "base_sources": {
    "expected_count": 15,
    "seen_count": 14,
    "missing_count": 1,
    "seen": [
      "eu_eurlex_dir_1993_13",
      "pl_courts_wloclawek_I_Ca_56_2018",
      "pl_eli_du_2001_733",
      "pl_isap_wdu19640160093",
      "pl_lex_art_19a",
      "pl_lex_kc_art_118",
      "pl_lex_ochrona_praw_lokatorow",
      "pl_saos_171957",
      "pl_sn_III_CZP_58-02",
      "pl_sn_II_CSK_862-14",
      "pl_sn_I_CNP_31-13_html",
      "pl_sn_I_CSK_292-12",
      "pl_sn_V_CSK_480-18_html",
      "pl_uokik_RKR_37_2013"
    ],
    "missing": [
      "pl_saos_search_kaucja_mieszkaniowa"
    ]
  },
  "expanded_sources_count": 0,
  "expanded_sources": [],
  "documents_count": 14,
  "documents": [
    {
      "source_id": "pl_uokik_RKR_37_2013",
      "doc_uid": "uokik_pl:urlsha:c506ff470f4740ad",
      "access_status": "OK",
      "title": "Untitled Document",
      "doc_type": "GUIDANCE",
      "license_tag": "OFFICIAL"
    },
    {
      "source_id": "eu_eurlex_dir_1993_13",
      "doc_uid": "eurlex_eu:dir/1993/13/oj/eng",
      "access_status": "OK",
      "title": "Directive - 93/13 - EN - Unfair Terms Directive - EUR-Lex",
      "doc_type": "EU_ACT",
      "license_tag": "OFFICIAL"
    },
    {
      "source_id": "pl_courts_wloclawek_I_Ca_56_2018",
      "doc_uid": "courts_pl:urlsha:20c9c82554a6e7f2",
      "access_status": "ERROR",
      "title": "ERROR",
      "doc_type": "CASELAW",
      "license_tag": "OFFICIAL"
    },
    {
      "source_id": "pl_saos_171957",
      "doc_uid": "saos_pl:171957",
      "access_status": "ERROR",
      "title": "ERROR",
      "doc_type": "CASELAW",
      "license_tag": "OFFICIAL"
    },
    {
      "source_id": "pl_sn_I_CNP_31-13_html",
      "doc_uid": "sn_pl:I_CNP_31-13",
      "access_status": "OK",
      "title": "Untitled HTML Document",
      "doc_type": "CASELAW",
      "license_tag": "OFFICIAL"
    },
    {
      "source_id": "pl_sn_V_CSK_480-18_html",
      "doc_uid": "sn_pl:V_CSK_480-18",
      "access_status": "OK",
      "title": "SN",
      "doc_type": "CASELAW",
      "license_tag": "OFFICIAL"
    },
    {
      "source_id": "pl_sn_I_CSK_292-12",
      "doc_uid": "sn_pl:I_CSK_292-12",
      "access_status": "OK",
      "title": "WYROK \nW IMIENIU RZECZYPOSPOLITEJ POLSKIEJ",
      "doc_type": "CASELAW",
      "license_tag": "OFFICIAL"
    },
    {
      "source_id": "pl_sn_II_CSK_862-14",
      "doc_uid": "sn_pl:II_CSK_862-14",
      "access_status": "OK",
      "title": "WYROK \nW IMIENIU RZECZYPOSPOLITEJ POLSKIEJ",
      "doc_type": "CASELAW",
      "license_tag": "OFFICIAL"
    },
    {
      "source_id": "pl_sn_III_CZP_58-02",
      "doc_uid": "sn_pl:III_CZP_58-02",
      "access_status": "OK",
      "title": "Uchwała z dnia 26 września 2002 r., III CZP 58/02",
      "doc_type": "CASELAW",
      "license_tag": "OFFICIAL"
    },
    {
      "source_id": "pl_lex_kc_art_118",
      "doc_uid": "lex_pl:urlsha:c31ee8071848130d",
      "access_status": "RESTRICTED",
      "title": "LEX",
      "doc_type": "STATUTE_REF",
      "license_tag": "COMMERCIAL"
    },
    {
      "source_id": "pl_lex_art_19a",
      "doc_uid": "lex_pl:urlsha:4f0332a0f08cee51",
      "access_status": "RESTRICTED",
      "title": "LEX",
      "doc_type": "STATUTE_REF",
      "license_tag": "COMMERCIAL"
    },
    {
      "source_id": "pl_lex_ochrona_praw_lokatorow",
      "doc_uid": "lex_pl:urlsha:2c175d980032d2be",
      "access_status": "RESTRICTED",
      "title": "LEX",
      "doc_type": "STATUTE_REF",
      "license_tag": "COMMERCIAL"
    },
    {
      "source_id": "pl_isap_wdu19640160093",
      "doc_uid": "isap_pl:WDU19640160093",
      "access_status": "OK",
      "title": "Kodeks cywilny1)",
      "doc_type": "STATUTE",
      "license_tag": "OFFICIAL"
    },
    {
      "source_id": "pl_eli_du_2001_733",
      "doc_uid": "eli_pl:DU/2001/733",
      "access_status": "OK",
      "title": "USTAWA\nz dnia 21 czerwca 2001 r.",
      "doc_type": "STATUTE",
      "license_tag": "OFFICIAL"
    }
  ]
}